README.md
setup.py
ChromifyPro/Chromify.py
ChromifyPro/Color.py
ChromifyPro/Converter.py
ChromifyPro/__init__.py
ChromifyPro/chromify_template.zip
ChromifyPro/cli.py
ChromifyPro/utils.py
ChromifyPro.egg-info/PKG-INFO
ChromifyPro.egg-info/SOURCES.txt
ChromifyPro.egg-info/dependency_links.txt
ChromifyPro.egg-info/requires.txt
ChromifyPro.egg-info/top_level.txt
ChromifyPro/ext/MassiveColors.py
ChromifyPro/ext/__init__.py