Metadata-Version: 2.4
Name: ChromifyPro
Version: 1.0.0
Summary: Color conversion library
Author: tingkan
Author-email: tingyu@mail.lhu.edu.tw
Classifier: Programming Language :: Python :: 3
Classifier: Programming Language :: Python :: 3.6
Classifier: Programming Language :: Python :: 3.7
Classifier: Programming Language :: Python :: 3.8
Classifier: Programming Language :: Python :: 3.9
Classifier: Programming Language :: Python :: 3.10
Requires-Dist: termcolor>=2.1.0
Dynamic: author
Dynamic: author-email
Dynamic: classifier
Dynamic: description
Dynamic: description-content-type
Dynamic: requires-dist
Dynamic: summary
